cyclic_classes/__init__.py
cyclic_classes/classes.py
cyclic_classes/constants.py
cyclic_classes/context.py
cyclic_classes/decorators.py
cyclic_classes/exceptions.py
cyclic_classes/registered.py
cyclic_classes/utils.py
cyclic_classes-0.0.2.dist-info/LICENSE
cyclic_classes-0.0.2.dist-info/METADATA
cyclic_classes-0.0.2.dist-info/WHEEL
cyclic_classes-0.0.2.dist-info/top_level.txt
cyclic_classes-0.0.2.dist-info/RECORD
